kiara_plugin/jupyter/__init__.py
kiara_plugin/jupyter/data_types.py
kiara_plugin/jupyter/defaults.py
kiara_plugin/jupyter/entrypoints.py
kiara_plugin/jupyter/models.py
kiara_plugin/jupyter/py.typed
kiara_plugin/jupyter/version.txt
kiara_plugin/jupyter/modules/__init__.py
kiara_plugin/jupyter/pipelines/.gitkeep
kiara_plugin/jupyter/pipelines/__init__.py
kiara_plugin/jupyter/renderers/__init__.py
kiara_plugin/jupyter/renderers/job.py
kiara_plugin/jupyter/renderers/pipeline.py
kiara_plugin/jupyter/resources/.gitkeep
kiara_plugin/jupyter/resources/templates/job_desc/jupyter_notebook.ipynb.j2
kiara_plugin/jupyter/resources/templates/pipeline/jupyter_notebook.ipynb.j2
kiara_plugin/jupyter/resources/templates/pipeline/workflow_tutorial/jupyter_notebook_workflow.ipynb.j2
kiara_plugin/jupyter/resources/templates/pipeline/workflow_tutorial/workflow_information.j2
kiara_plugin/jupyter/resources/templates/pipeline/workflow_tutorial/workflow_inputs.j2
kiara_plugin/jupyter/resources/templates/pipeline/workflow_tutorial/workflow_outputs.j2
kiara_plugin/jupyter/resources/templates/pipeline/workflow_tutorial/workflow_snapshot.j2
kiara_plugin/jupyter/utils/__init__.py
kiara_plugin/jupyter/utils/graphs.py
kiara_plugin.jupyter-0.5.1.dist-info/AUTHORS.md
kiara_plugin.jupyter-0.5.1.dist-info/LICENSE
kiara_plugin.jupyter-0.5.1.dist-info/METADATA
kiara_plugin.jupyter-0.5.1.dist-info/WHEEL
kiara_plugin.jupyter-0.5.1.dist-info/entry_points.txt
kiara_plugin.jupyter-0.5.1.dist-info/top_level.txt
kiara_plugin.jupyter-0.5.1.dist-info/RECORD
