Metadata-Version: 2.1
Name: kiara_plugin.jupyter
Version: 0.5.1
Summary: Jupyter integration for kiara
Author-email: Markus Binsteiner <markus@frkl.io>
License: MPL-2.0
Project-URL: homepage, https://github.com/DHARPA-Project/kiara_plugin.jupyter
Project-URL: documentation, https://DHARPA-Project.github.io/kiara_plugin.jupyter
Project-URL: repository, https://github.com/DHARPA-Project/kiara_plugin.jupyter
Keywords: kiara
Classifier: Programming Language :: Python :: 3
Classifier: Development Status :: 3 - Alpha
Classifier: License :: OSI Approved :: Mozilla Public License 2.0 (MPL 2.0)
Classifier: Programming Language :: Python
Classifier: Programming Language :: Python :: 3
Classifier: Programming Language :: Python :: 3 :: Only
Classifier: Programming Language :: Python :: 3.9
Classifier: Programming Language :: Python :: 3.10
Classifier: Programming Language :: Python :: 3.11
Classifier: Programming Language :: Python :: 3.11
Requires-Python: >=3.9
License-File: LICENSE
License-File: AUTHORS.md
Requires-Dist: pip>=23.0.0
Requires-Dist: importlib-metadata<8.0.0,>=3.0.0.0
Requires-Dist: ipywidgets>=8.0.0
Requires-Dist: ipydagred3>=0.3.7
Requires-Dist: jupytext>=1.14.0
Requires-Dist: black>=21.0.0
Requires-Dist: rich>=0.13.0.0
Provides-Extra: jupyter
Requires-Dist: jupyterlab; extra == "jupyter"
Provides-Extra: kiara
Requires-Dist: kiara_plugin.tabular>=0.5.4; extra == "kiara"
Requires-Dist: kiara_plugin.onboarding>=0.5.0; extra == "kiara"
Provides-Extra: dev-documentation
Requires-Dist: kiara[dev_documentation]; extra == "dev-documentation"
Provides-Extra: dev-testing
Requires-Dist: kiara[dev_testing]; extra == "dev-testing"
Requires-Dist: kiara_plugin.core_types>=0.5.1; extra == "dev-testing"
Requires-Dist: nbconvert>=7.16.0; extra == "dev-testing"
Provides-Extra: dev-utils
Requires-Dist: kiara[dev_utils]; extra == "dev-utils"
